defopt.py
defopt-7.0.0.dist-info/licenses/LICENSE.txt
defopt-7.0.0.dist-info/METADATA
defopt-7.0.0.dist-info/WHEEL
defopt-7.0.0.dist-info/top_level.txt
defopt-7.0.0.dist-info/RECORD
