Metadata-Version: 2.4
Name: defopt
Version: 7.0.0
Summary: Effortless argument parser
Author: Antony Lee
Project-URL: Repository, https://github.com/anntzer/defopt
Keywords: argument parser,optparse,argparse,getopt,docopt,sphinx
Classifier: Programming Language :: Python :: 3
Classifier: Operating System :: OS Independent
Classifier: Development Status :: 5 - Production/Stable
Classifier: Intended Audience :: Developers
Requires-Python: >=3.7
License-File: LICENSE.txt
Requires-Dist: docutils>=0.12
Requires-Dist: sphinxcontrib-napoleon>=0.7.0
Requires-Dist: importlib_metadata>=1.0; python_version < "3.8"
Requires-Dist: typing_inspect>=0.8.0; python_version < "3.8"
Requires-Dist: pkgutil_resolve_name; python_version < "3.9"
Requires-Dist: colorama>=0.3.4; sys_platform == "win32"
Provides-Extra: docs
Requires-Dist: sphinx>=4.4; extra == "docs"
Dynamic: license-file
